LICENSE
MANIFEST.in
README.md
build.zig
build.zig.zon
pyproject.toml
setup.py
tokenizerz.py
src/tokenizer.zig
tokenizerz.egg-info/PKG-INFO
tokenizerz.egg-info/SOURCES.txt
tokenizerz.egg-info/dependency_links.txt
tokenizerz.egg-info/entry_points.txt
tokenizerz.egg-info/not-zip-safe
tokenizerz.egg-info/requires.txt
tokenizerz.egg-info/top_level.txt