Metadata-Version: 2.4
Name: tokenizerz
Version: 0.0.3a5
Summary: Minimal BPE tokenizer in Zig
Home-page: https://github.com/jaco-bro/tokenizer
Author: J Joe
Author-email: backupjjoe@gmail.com
License-File: LICENSE
Requires-Dist: ziglang==0.13.0.post1
Requires-Dist: jinja2
Dynamic: author
Dynamic: author-email
Dynamic: description
Dynamic: description-content-type
Dynamic: home-page
Dynamic: license-file
Dynamic: requires-dist
Dynamic: summary
